{"id": "https://openalex.org/A5068689349", "orcid": null, "display_name": "YC Rhie", "display_name_alternatives": ["YC Rhie"], "works_count": 1, "cited_by_count": 0, "summary_stats": {"2yr_mean_citedness": 0.0, "h_index": 0, "i10_index": 0}, "ids": {"openalex": "https://openalex.org/A5068689349"}, "affiliations": [], "last_known_institution": null, "last_known_institutions": [], "topics": [{"id": "https://openalex.org/T13005", "display_name": "Occultism and Modernity", "count": 1, "subfield": {"id": "https://openalex.org/subfields/1211", "display_name": "Philosophy"}, "field": {"id": "https://openalex.org/fields/12", "display_name": "Arts and Humanities"}, "domain": {"id": "https://openalex.org/domains/2", "display_name": "Social Sciences"}}], "topic_share": [{"id": "https://openalex.org/T13005", "display_name": "Occultism and Modernity", "value": 1.33e-05, "subfield": {"id": "https://openalex.org/subfields/1211", "display_name": "Philosophy"}, "field": {"id": "https://openalex.org/fields/12", "display_name": "Arts and Humanities"}, "domain": {"id": "https://openalex.org/domains/2", "display_name": "Social Sciences"}}], "x_concepts": [{"id": "https://openalex.org/C1276947", "wikidata": "https://www.wikidata.org/wiki/Q333", "display_name": "Astronomy", "level": 1, "score": 100.0}, {"id": "https://openalex.org/C24667770", "wikidata": "https://www.wikidata.org/wiki/Q34187", "display_name": "Religious studies", "level": 1, "score": 100.0}, {"id": "https://openalex.org/C24890656", "wikidata": "https://www.wikidata.org/wiki/Q82811", "display_name": "Acoustics", "level": 1, "score": 100.0}, {"id": "https://openalex.org/C27206212", "wikidata": "https://www.wikidata.org/wiki/Q34178", "display_name": "Theology", "level": 1, "score": 100.0}, {"id": "https://openalex.org/C44870925", "wikidata": "https://www.wikidata.org/wiki/Q37547", "display_name": "Astrophysics", "level": 1, "score": 100.0}, {"id": "https://openalex.org/C62520636", "wikidata": "https://www.wikidata.org/wiki/Q944", "display_name": "Quantum mechanics", "level": 1, "score": 100.0}, {"id": "https://openalex.org/C71924100", "wikidata": "https://www.wikidata.org/wiki/Q11190", "display_name": "Medicine", "level": 0, "score": 100.0}, {"id": "https://openalex.org/C95457728", "wikidata": "https://www.wikidata.org/wiki/Q309", "display_name": "History", "level": 0, "score": 100.0}, {"id": "https://openalex.org/C111472728", "wikidata": "https://www.wikidata.org/wiki/Q9471", "display_name": "Epistemology", "level": 1, "score": 100.0}, {"id": "https://openalex.org/C121332964", "wikidata": "https://www.wikidata.org/wiki/Q413", "display_name": "Physics", "level": 0, "score": 100.0}, {"id": "https://openalex.org/C124952713", "wikidata": "https://www.wikidata.org/wiki/Q8242", "display_name": "Literature", "level": 1, "score": 100.0}, {"id": "https://openalex.org/C128536511", "wikidata": "https://www.wikidata.org/wiki/Q846742", "display_name": "History of religions", "level": 2, "score": 100.0}, {"id": "https://openalex.org/C138885662", "wikidata": "https://www.wikidata.org/wiki/Q5891", "display_name": "Philosophy", "level": 0, "score": 100.0}, {"id": "https://openalex.org/C142362112", "wikidata": "https://www.wikidata.org/wiki/Q735", "display_name": "Art", "level": 0, "score": 100.0}, {"id": "https://openalex.org/C142724271", "wikidata": "https://www.wikidata.org/wiki/Q7208", "display_name": "Pathology", "level": 1, "score": 100.0}, {"id": "https://openalex.org/C166957645", "wikidata": "https://www.wikidata.org/wiki/Q23498", "display_name": "Archaeology", "level": 1, "score": 100.0}, {"id": "https://openalex.org/C204787440", "wikidata": "https://www.wikidata.org/wiki/Q188504", "display_name": "Alternative medicine", "level": 2, "score": 100.0}, {"id": "https://openalex.org/C205649164", "wikidata": "https://www.wikidata.org/wiki/Q1071", "display_name": "Geography", "level": 0, "score": 100.0}, {"id": "https://openalex.org/C512209198", "wikidata": "https://www.wikidata.org/wiki/Q42042", "display_name": "Shamanism", "level": 2, "score": 100.0}, {"id": "https://openalex.org/C514793146", "wikidata": "https://www.wikidata.org/wiki/Q168796", "display_name": "Spirituality", "level": 3, "score": 100.0}, {"id": "https://openalex.org/C534701709", "wikidata": "https://www.wikidata.org/wiki/Q19786", "display_name": "Old Testament", "level": 2, "score": 100.0}, {"id": "https://openalex.org/C2777025665", "wikidata": "https://www.wikidata.org/wiki/Q484692", "display_name": "Hymn", "level": 2, "score": 100.0}, {"id": "https://openalex.org/C2777704519", "wikidata": "https://www.wikidata.org/wiki/Q45732", "display_name": "MAGIC (telescope)", "level": 2, "score": 100.0}, {"id": "https://openalex.org/C2780211513", "wikidata": "https://www.wikidata.org/wiki/Q1132167", "display_name": "Discernment", "level": 2, "score": 100.0}], "counts_by_year": [{"year": 2013, "works_count": 1, "cited_by_count": 0}], "works_api_url": "https://api.openalex.org/works?filter=author.id:A5068689349", "updated_date": "2024-04-10T17:14:31.622172", "created_date": "2023-07-21"}