{"id": "https://openalex.org/A5015882669", "orcid": null, "display_name": "Eugene I. Knez", "display_name_alternatives": ["Eugene Knez", "Eugene I. Knez", "Eugene Irving Knez"], "works_count": 11, "cited_by_count": 21, "summary_stats": {"2yr_mean_citedness": 0.0, "h_index": 2, "i10_index": 1}, "ids": {"openalex": "https://openalex.org/A5015882669"}, "affiliations": [{"institution": {"id": "https://openalex.org/I103187081", "ror": "https://ror.org/01pp8nd67", "display_name": "Smithsonian Institution", "country_code": "US", "type": "government", "lineage": ["https://openalex.org/I103187081"]}, "years": [1972, 1966]}, {"institution": {"id": "https://openalex.org/I1300065529", "ror": "https://ror.org/04a5aqx80", "display_name": "Museum of Indian Arts and Culture", "country_code": "US", "type": "archive", "lineage": ["https://openalex.org/I1300065529"]}, "years": [1970]}], "last_known_institution": {"id": "https://openalex.org/I103187081", "ror": "https://ror.org/01pp8nd67", "display_name": "Smithsonian Institution", "country_code": "US", "type": "government", "lineage": ["https://openalex.org/I103187081"]}, "last_known_institutions": [{"id": "https://openalex.org/I103187081", "ror": "https://ror.org/01pp8nd67", "display_name": "Smithsonian Institution", "country_code": "US", "type": "government", "lineage": ["https://openalex.org/I103187081"]}], "x_concepts": [{"id": "https://openalex.org/C95457728", "wikidata": "https://www.wikidata.org/wiki/Q309", "display_name": "History", "level": 0, "score": 90.9}, {"id": "https://openalex.org/C17744445", "wikidata": "https://www.wikidata.org/wiki/Q36442", "display_name": "Political science", "level": 0, "score": 72.7}, {"id": "https://openalex.org/C199539241", "wikidata": "https://www.wikidata.org/wiki/Q7748", "display_name": "Law", "level": 1, "score": 72.7}, {"id": "https://openalex.org/C41008148", "wikidata": "https://www.wikidata.org/wiki/Q21198", "display_name": "Computer science", "level": 0, "score": 63.6}, {"id": "https://openalex.org/C205649164", "wikidata": "https://www.wikidata.org/wiki/Q1071", "display_name": "Geography", "level": 0, "score": 54.5}, {"id": "https://openalex.org/C138885662", "wikidata": "https://www.wikidata.org/wiki/Q5891", "display_name": "Philosophy", "level": 0, "score": 45.5}, {"id": "https://openalex.org/C142362112", "wikidata": "https://www.wikidata.org/wiki/Q735", "display_name": "Art", "level": 0, "score": 45.5}, {"id": "https://openalex.org/C161191863", "wikidata": "https://www.wikidata.org/wiki/Q199655", "display_name": "Library science", "level": 1, "score": 45.5}, {"id": "https://openalex.org/C41895202", "wikidata": "https://www.wikidata.org/wiki/Q8162", "display_name": "Linguistics", "level": 1, "score": 36.4}, {"id": "https://openalex.org/C52119013", "wikidata": "https://www.wikidata.org/wiki/Q50637", "display_name": "Art history", "level": 1, "score": 36.4}, {"id": "https://openalex.org/C136764020", "wikidata": "https://www.wikidata.org/wiki/Q466", "display_name": "World Wide Web", "level": 1, "score": 36.4}, {"id": "https://openalex.org/C19165224", "wikidata": "https://www.wikidata.org/wiki/Q23404", "display_name": "Anthropology", "level": 1, "score": 27.3}, {"id": "https://openalex.org/C144024400", "wikidata": "https://www.wikidata.org/wiki/Q21201", "display_name": "Sociology", "level": 0, "score": 27.3}, {"id": "https://openalex.org/C166957645", "wikidata": "https://www.wikidata.org/wiki/Q23498", "display_name": "Archaeology", "level": 1, "score": 27.3}, {"id": "https://openalex.org/C2778805511", "wikidata": "https://www.wikidata.org/wiki/Q1713", "display_name": "Citation", "level": 2, "score": 27.3}], "counts_by_year": [{"year": 2021, "works_count": 0, "cited_by_count": 1}, {"year": 2018, "works_count": 0, "cited_by_count": 1}, {"year": 2016, "works_count": 0, "cited_by_count": 2}, {"year": 2015, "works_count": 0, "cited_by_count": 1}, {"year": 2014, "works_count": 0, "cited_by_count": 2}, {"year": 2013, "works_count": 0, "cited_by_count": 2}], "works_api_url": "https://api.openalex.org/works?filter=author.id:A5015882669", "updated_date": "2024-03-20T03:08:43.463400", "created_date": "2023-07-21"}