[{"id": "https://openalex.org/W3023152408", "doi": "https://doi.org/10.3390/rel11050231", "title": "Syncretism, Harmonization, and Mutual Appropriation between Buddhism and Confucianism in Pre-Joseon Korea", "display_name": "Syncretism, Harmonization, and Mutual Appropriation between Buddhism and Confucianism in Pre-Joseon Korea", "publication_year": 2020, "publication_date": "2020-05-08", "ids": {"openalex": "https://openalex.org/W3023152408", "doi": "https://doi.org/10.3390/rel11050231", "mag": "3023152408"}, "language": "en", "primary_location": {"is_oa": true, "landing_page_url": "https://doi.org/10.3390/rel11050231", "pdf_url": "https://www.mdpi.com/2077-1444/11/5/231/pdf?version=1589180803", "source": {"id": "https://openalex.org/S4210184657", "display_name": "Religions (Basel)", "issn_l": "2077-1444", "issn": ["2077-1444"], "is_oa": true, "is_in_doaj": true, "host_organization": "https://openalex.org/P4310310987", "host_organization_name": "Multidisciplinary Digital Publishing Institute", "host_organization_lineage": ["https://openalex.org/P4310310987"], "host_organization_lineage_names": ["Multidisciplinary Digital Publishing Institute"], "type": "journal"}, "license": "cc-by", "version": "publishedVersion", "is_accepted": true, "is_published": true}, "type": "article", "type_crossref": "journal-article", "indexed_in": ["crossref", "doaj"], "open_access": {"is_oa": true, "oa_status": "gold", "oa_url": "https://www.mdpi.com/2077-1444/11/5/231/pdf?version=1589180803", "any_repository_has_fulltext": false}, "authorships": [{"author_position": "first", "author": {"id": "https://openalex.org/A5001285749", "display_name": "Sem Vermeersch", "orcid": "https://orcid.org/0000-0002-5258-6424"}, "institutions": [{"id": "https://openalex.org/I139264467", "display_name": "Seoul National University", "ror": "https://ror.org/04h9pn542", "country_code": "KR", "type": "education", "lineage": ["https://openalex.org/I139264467"]}], "countries": ["KR"], "is_corresponding": true, "raw_author_name": "Sem Vermeersch", "raw_affiliation_string": "Department of Religious Studies, Seoul National University, Seoul 08826, Korea", "raw_affiliation_strings": ["Department of Religious Studies, Seoul National University, Seoul 08826, Korea"]}], "countries_distinct_count": 1, "institutions_distinct_count": 1, "corresponding_author_ids": ["https://openalex.org/A5001285749"], "corresponding_institution_ids": ["https://openalex.org/I139264467"], "apc_list": {"value": 1200, "currency": "CHF", "value_usd": 1299, "provenance": "doaj"}, "apc_paid": {"value": 1200, "currency": "CHF", "value_usd": 1299, "provenance": "doaj"}, "has_fulltext": true, "fulltext_origin": "pdf", "cited_by_count": 3, "cited_by_percentile_year": {"min": 78, "max": 81}, "biblio": {"volume": "11", "issue": "5", "first_page": "231", "last_page": "231"}, "is_retracted": false, "is_paratext": false, "primary_topic": {"id": "https://openalex.org/T10893", "display_name": "Religious Diversity and Regulation in Chinese Society", "score": 0.9928, "subfield": {"id": "https://openalex.org/subfields/3312", "display_name": "Sociology and Political Science"}, "field": {"id": "https://openalex.org/fields/33", "display_name": "Social Sciences"}, "domain": {"id": "https://openalex.org/domains/2", "display_name": "Social Sciences"}}, "topics": [{"id": "https://openalex.org/T10893", "display_name": "Religious Diversity and Regulation in Chinese Society", "score": 0.9928, "subfield": {"id": "https://openalex.org/subfields/3312", "display_name": "Sociology and Political Science"}, "field": {"id": "https://openalex.org/fields/33", "display_name": "Social Sciences"}, "domain": {"id": "https://openalex.org/domains/2", "display_name": "Social Sciences"}}, {"id": "https://openalex.org/T11198", "display_name": "Cultural Dynamics in Japan and East Asia", "score": 0.9892, "subfield": {"id": "https://openalex.org/subfields/3316", "display_name": "Cultural Studies"}, "field": {"id": "https://openalex.org/fields/33", "display_name": "Social Sciences"}, "domain": {"id": "https://openalex.org/domains/2", "display_name": "Social Sciences"}}, {"id": "https://openalex.org/T13303", "display_name": "Global Impact of Korean Popular Culture", "score": 0.932, "subfield": {"id": "https://openalex.org/subfields/3316", "display_name": "Cultural Studies"}, "field": {"id": "https://openalex.org/fields/33", "display_name": "Social Sciences"}, "domain": {"id": "https://openalex.org/domains/2", "display_name": "Social Sciences"}}], "keywords": [{"keyword": "confucianism", "score": 0.5929}, {"keyword": "buddhism", "score": 0.5128}, {"keyword": "syncretism", "score": 0.4275}, {"keyword": "harmonization", "score": 0.3814}, {"keyword": "mutual appropriation", "score": 0.373}, {"keyword": "pre-joseon", "score": 0.25}], "concepts": [{"id": "https://openalex.org/C2780158765", "wikidata": "https://www.wikidata.org/wiki/Q2004759", "display_name": "Syncretism (linguistics)", "level": 2, "score": 0.9650403}, {"id": "https://openalex.org/C75699723", "wikidata": "https://www.wikidata.org/wiki/Q748", "display_name": "Buddhism", "level": 2, "score": 0.92690825}, {"id": "https://openalex.org/C2776931063", "wikidata": "https://www.wikidata.org/wiki/Q4781738", "display_name": "Appropriation", "level": 2, "score": 0.7647817}, {"id": "https://openalex.org/C191935318", "wikidata": "https://www.wikidata.org/wiki/Q148", "display_name": "China", "level": 2, "score": 0.70795727}, {"id": "https://openalex.org/C2779962950", "wikidata": "https://www.wikidata.org/wiki/Q5659376", "display_name": "Harmonization", "level": 2, "score": 0.55347466}, {"id": "https://openalex.org/C138885662", "wikidata": "https://www.wikidata.org/wiki/Q5891", "display_name": "Philosophy", "level": 0, "score": 0.45890728}, {"id": "https://openalex.org/C24667770", "wikidata": "https://www.wikidata.org/wiki/Q34187", "display_name": "Religious studies", "level": 1, "score": 0.44134378}, {"id": "https://openalex.org/C111472728", "wikidata": "https://www.wikidata.org/wiki/Q9471", "display_name": "Epistemology", "level": 1, "score": 0.28447548}, {"id": "https://openalex.org/C107038049", "wikidata": "https://www.wikidata.org/wiki/Q35986", "display_name": "Aesthetics", "level": 1, "score": 0.25854456}, {"id": "https://openalex.org/C17744445", "wikidata": "https://www.wikidata.org/wiki/Q36442", "display_name": "Political science", "level": 0, "score": 0.23713678}, {"id": "https://openalex.org/C199539241", "wikidata": "https://www.wikidata.org/wiki/Q7748", "display_name": "Law", "level": 1, "score": 0.16033778}, {"id": "https://openalex.org/C27206212", "wikidata": "https://www.wikidata.org/wiki/Q34178", "display_name": "Theology", "level": 1, "score": 0.13492888}, {"id": "https://openalex.org/C41895202", "wikidata": "https://www.wikidata.org/wiki/Q8162", "display_name": "Linguistics", "level": 1, "score": 0.123958915}], "mesh": [], "locations_count": 2, "locations": [{"is_oa": true, "landing_page_url": "https://doi.org/10.3390/rel11050231", "pdf_url": "https://www.mdpi.com/2077-1444/11/5/231/pdf?version=1589180803", "source": {"id": "https://openalex.org/S4210184657", "display_name": "Religions (Basel)", "issn_l": "2077-1444", "issn": ["2077-1444"], "is_oa": true, "is_in_doaj": true, "host_organization": "https://openalex.org/P4310310987", "host_organization_name": "Multidisciplinary Digital Publishing Institute", "host_organization_lineage": ["https://openalex.org/P4310310987"], "host_organization_lineage_names": ["Multidisciplinary Digital Publishing Institute"], "type": "journal"}, "license": "cc-by", "version": "publishedVersion", "is_accepted": true, "is_published": true}, {"is_oa": false, "landing_page_url": "https://doaj.org/article/52098f9d00c943c1bff051e6b13affb2", "pdf_url": null, "source": {"id": "https://openalex.org/S4306401280", "display_name": "DOAJ (DOAJ: Directory of Open Access Journals)", "issn_l": null, "issn": null, "is_oa": true, "is_in_doaj": false, "host_organization": null, "host_organization_name": null, "host_organization_lineage": [], "host_organization_lineage_names": [], "type": "repository"}, "license": null, "version": null, "is_accepted": false, "is_published": false}], "best_oa_location": {"is_oa": true, "landing_page_url": "https://doi.org/10.3390/rel11050231", "pdf_url": "https://www.mdpi.com/2077-1444/11/5/231/pdf?version=1589180803", "source": {"id": "https://openalex.org/S4210184657", "display_name": "Religions (Basel)", "issn_l": "2077-1444", "issn": ["2077-1444"], "is_oa": true, "is_in_doaj": true, "host_organization": "https://openalex.org/P4310310987", "host_organization_name": "Multidisciplinary Digital Publishing Institute", "host_organization_lineage": ["https://openalex.org/P4310310987"], "host_organization_lineage_names": ["Multidisciplinary Digital Publishing Institute"], "type": "journal"}, "license": "cc-by", "version": "publishedVersion", "is_accepted": true, "is_published": true}, "sustainable_development_goals": [{"display_name": "Reduced inequalities", "score": 0.52, "id": "https://metadata.un.org/sdg/10"}], "grants": [], "versions": [], "referenced_works_count": 8, "referenced_works": ["https://openalex.org/W328681753", "https://openalex.org/W1993561129", "https://openalex.org/W1999526576", "https://openalex.org/W2045970356", "https://openalex.org/W2052983465", "https://openalex.org/W2895699447", "https://openalex.org/W3000053527", "https://openalex.org/W4232565699"], "related_works": ["https://openalex.org/W1561276147", "https://openalex.org/W4246620847", "https://openalex.org/W1983423431", "https://openalex.org/W2071326889", "https://openalex.org/W2486640460", "https://openalex.org/W2385082606", "https://openalex.org/W2767754190", "https://openalex.org/W2795137380", "https://openalex.org/W3098347898", "https://openalex.org/W2394419880"], "ngrams_url": "https://api.openalex.org/works/W3023152408/ngrams", "abstract_inverted_index": {"Following": [0], "the": [1, 44, 58, 68, 83, 107, 123, 131, 140], "introduction": [2], "of": [3, 9, 21, 35, 52, 70, 85, 91, 110, 122], "Buddhism": [4, 28, 134], "to": [5, 18, 42, 77], "China,": [6, 130], "various": [7], "strategies": [8], "accommodation": [10], "with": [11, 23, 37], "Chinese": [12, 24], "culture": [13], "were": [14, 49], "developed,": [15], "all": [16], "amounting": [17], "some": [19, 78], "form": [20], "syncretism": [22, 86], "religions,": [25], "mainly": [26], "Confucianism.": [27, 38], "in": [29, 103, 129, 149], "pre-modern": [30], "Korea": [31, 105], "displayed": [32], "similar": [33], "forms": [34, 51], "interaction": [36], "This": [39, 93], "article": [40, 94], "aims": [41], "critique": [43], "notion": [45], "that": [46, 96], "such": [47], "interactions": [48], "merely": [50], "\u201charmonization\u201d,": [53], "finding": [54], "common": [55], "ground": [56], "between": [57], "traditions.": [59], "If": [60], "one": [61], "religion": [62], "borrows": [63], "from": [64, 139], "another": [65, 71], "or": [66], "adopts": [67], "message": [69], "religion,": [72], "it": [73], "will": [74], "be": [75], "affected": [76], "degree,": [79], "which": [80], "is": [81, 87], "why": [82], "concept": [84], "a": [88, 99, 117, 136], "better": [89], "tool": [90], "analysis.": [92], "concludes": [95], "there": [97], "was": [98, 145], "strong": [100], "official": [101], "support": [102], "Goryeo": [104], "towards": [106], "genuine": [108], "convergence": [109], "Confucianism": [111, 128, 138], "and": [112], "Buddhism.": [113], "Since": [114], "Buddhism,": [115], "as": [116], "result,": [118], "took": [119], "on": [120], "many": [121], "tasks": [124], "carried": [125], "out": [126], "by": [127, 135], "reaction": [132], "against": [133], "reinvigorated": [137], "late": [141], "fourteenth": [142], "century": [143], "onward": [144], "much": [146], "stronger": [147], "than": [148], "China.": [150]}, "cited_by_api_url": "https://api.openalex.org/works?filter=cites:W3023152408", "counts_by_year": [{"year": 2023, "cited_by_count": 1}, {"year": 2021, "cited_by_count": 2}], "updated_date": "2024-03-31T04:57:44.967524", "created_date": "2020-05-13"}]